{"empires":{"$adv":{"statemilitary":["statemilitary"],"root":["technology"],"agriculture":["agriculture"],"ballistics":["ballistics"],"bronzeworking":["bronzeworking"],"cartography":["cartography"],"colonialism":["colonialism"],"construction":["construction"],"croprotation":["croprotation"],"currency":["currency"],"fertilizer":["fertilizer"],"guilds":["guilds"],"gunpowder":["gunpowder"],"horsebackriding":["horsebackriding"],"humanism":["humanism"],"industrialization":["industrialization"],"ironworking":["ironworking"],"irrigation":["irrigation"],"machinery":["machinery"],"drama":["drama"],"mercantilism":["mercantilism"],"mining":["mining"],"navigation":["navigation"],"philosophy":["philosophy"],"pottery":["pottery"],"printing":["printing"],"recreation":["recreation"],"sailing":["sailing"],"steampower":["steampower"],"stonemasonry":["stonemasonry"],"wheel":["wheel"],"writing":["writing"]}}}