{
    "__comment": "Made with TheDestruc7i0n's advancements generator: https://advancements.thedestruc7i0n.ca",
    "display": {
        "title": {
            "text": "Writing"
        },
        "description": {
            "text": "Description"
        },
        "icon": {
            "item": "minecraft:popped_chorus_fruit"
        },
        "frame": "task",
        "show_toast": true,
        "announce_to_chat": true,
        "hidden": false
    },
    "criteria": {
        "writing": {
            "trigger": "minecraft:impossible"
        }
    },
    "parent": "empires:farming"
}